ligand/__init__.py
ligand/daemon.py
ligand/exceptions.py
ligand/job.py
ligand/version.py
ligand/bin/ligand-daemon
ligand/servicepb/__init__.py
ligand/servicepb/latch_pb2.py
ligand/servicepb/latch_pb2_grpc.py
ligand-0.0.2.data/scripts/ligand
ligand-0.0.2.dist-info/METADATA
ligand-0.0.2.dist-info/WHEEL
ligand-0.0.2.dist-info/top_level.txt
ligand-0.0.2.dist-info/RECORD
