Metadata-Version: 2.1
Name: ligand
Version: 0.0.2
Summary: train on the cloud with one line of code
Home-page: https://latch.ai
Author-email: kennyworkman@berkeley.edu
License: Apache License 2.0
Platform: UNKNOWN
Requires-Python: >=3.6.0
Requires-Dist: googleapis-common-protos[grpc] (>=1.0.0)
